{
  "Pages": [
    {
      "Page": "Five Things That You Already Accomplished",
      "id": "1"
    },
    {
      "Page": "What Do You Want, In The Next 10 Years?",
      "id": "2"
    }
  ],
  "Something": [
    {
      "accomp": "newNewTest",
      "id": "0b66"
    },
    {
      "id": "9cc5",
      "accomp": "Fifth"
    },
    {
      "id": "d5be",
      "accomp": "new one"
    },
    {
      "id": "ffff",
      "accomp": "abcd"
    },
    {
      "id": "8259",
      "accomp": "abcde"
    }
  ],
  "Goal": [
    {
      "theGoal": "Testing",
      "yearGoal": "1 Year Goal",
      "id": "70ab"
    },
    {
      "id": "e66e",
      "theGoal": "Make Music",
      "yearGoal": "1 Year Goal"
    },
    {
      "id": "eff5",
      "theGoal": "Buff me up",
      "yearGoal": "1 Year Goal"
    },
    {
      "theGoal": "3 year goal",
      "yearGoal": "1 Year Goal",
      "id": "cf91"
    },
    {
      "id": "d63c",
      "theGoal": "5 year goal",
      "yearGoal": "5 Year Goal"
    },
    {
      "theGoal": "Reload",
      "id": "e5ef"
    },
    {
      "id": "b4d3",
      "theGoal": "Ben 10",
      "yearGoal": "10 Year Goal"
    },
    {
      "id": "117c",
      "theGoal": "test2",
      "yearGoal": "10 Year Goal"
    },
    {
      "id": "7bcc",
      "theGoal": "test3",
      "yearGoal": "5 Year Goal"
    },
    {
      "id": "de34",
      "theGoal": "test4",
      "yearGoal": "5 Year Goal"
    },
    {
      "id": "def5",
      "theGoal": "abcdefghi",
      "yearGoal": "10 Year Goal"
    }
  ]
}